README.md
setup.py
hamonsoft/__init__.py
hamonsoft/logging/LogWriter.py
hamonsoft/logging/__init__.py
hamonsoft/logging/log_loader.py
hamonsoft_ai_log.egg-info/PKG-INFO
hamonsoft_ai_log.egg-info/SOURCES.txt
hamonsoft_ai_log.egg-info/dependency_links.txt
hamonsoft_ai_log.egg-info/top_level.txt