Metadata-Version: 2.1
Name: hamonsoft-ai-log
Version: 0.0.5
Summary: Hamonsoft Company Database Python Version Package
Author: Hamonsoft AI
License: MIT
Requires-Python: >=3.7, <4
